physical_dualism.py
physical_dualism-1.0.1.dist-info/DESCRIPTION.rst
physical_dualism-1.0.1.dist-info/METADATA
physical_dualism-1.0.1.dist-info/RECORD
physical_dualism-1.0.1.dist-info/WHEEL
physical_dualism-1.0.1.dist-info/metadata.json
physical_dualism-1.0.1.dist-info/top_level.txt
