Metadata-Version: 2.0
Name: physical-dualism
Version: 1.0.1
Summary: Python library that approximates the natural frequency from stress via physical dualism, and vice versa.
Home-page: https://github.com/petarmaric/physical_dualism
Author: Petar Maric
Author-email: petarmaric@uns.ac.rs
License: BSD
Platform: any
Classifier: Development Status :: 5 - Production/Stable
Classifier: Intended Audience :: Developers
Classifier: License :: OSI Approved :: BSD License
Classifier: Intended Audience :: Developers
Classifier: Intended Audience :: Science/Research
Classifier: Operating System :: OS Independent
Classifier: Programming Language :: Python :: 2.7
Classifier: Topic :: Scientific/Engineering
Classifier: Topic :: Scientific/Engineering :: Physics
Requires-Dist: numpy (>=1.11,<2.0)
